pixiedust_twitterdemo1/__init__.py
pixiedust_twitterdemo1/twitterDemo.py
pixiedust_twitterdemo1-0.1.dist-info/DESCRIPTION.rst
pixiedust_twitterdemo1-0.1.dist-info/METADATA
pixiedust_twitterdemo1-0.1.dist-info/RECORD
pixiedust_twitterdemo1-0.1.dist-info/WHEEL
pixiedust_twitterdemo1-0.1.dist-info/metadata.json
pixiedust_twitterdemo1-0.1.dist-info/top_level.txt
