Metadata-Version: 2.0
Name: pixiedust-twitterdemo1
Version: 0.1
Summary: Pixiedust demo of the Twitter Sentiment Analysis tutorials
Home-page: https://github.com/lgellis/STEM-twitter-wall/tree/master/twitterdemo
Author: David Taieb the genius and slightly hacked by STEM Women
Author-email: david_taieb@us.ibm.com
License: Apache 2.0
Platform: UNKNOWN
Requires-Dist: pixiedust
